coconut/__init__.py
coconut/api.py
coconut/client.py
coconut/config.py
coconut/error.py
coconut/job.py
coconut/metadata.py
coconut/version.py
heywatch/__init__.py
heywatch/api.py
coconutpy-3.0.0.dist-info/METADATA
coconutpy-3.0.0.dist-info/WHEEL
coconutpy-3.0.0.dist-info/top_level.txt
coconutpy-3.0.0.dist-info/RECORD
