Metadata-Version: 2.1
Name: coconutpy
Version: 3.0.0
Summary: A python wrapper around the Coconut API
Home-page: https://coconut.co
Author: Coconut
Author-email: team@coconut.co
License: MIT License
Keywords: coconut video encoding api
Platform: UNKNOWN
Requires-Dist: httplib2
